JavascriptQingliangjiHanshuShiBiancheng/README.md
JavascriptQingliangjiHanshuShiBiancheng/__init__.py
JavascriptQingliangjiHanshuShiBiancheng/__main__.py
JavascriptQingliangjiHanshuShiBiancheng/file.epub
JavascriptQingliangjiHanshuShiBiancheng/index.html
JavascriptQingliangjiHanshuShiBiancheng/css/__init__.py
JavascriptQingliangjiHanshuShiBiancheng/css/annotations.css
JavascriptQingliangjiHanshuShiBiancheng/css/main.css
JavascriptQingliangjiHanshuShiBiancheng/css/normalize.css
JavascriptQingliangjiHanshuShiBiancheng/css/popup.css
JavascriptQingliangjiHanshuShiBiancheng/font/__init__.py
JavascriptQingliangjiHanshuShiBiancheng/font/fontello.eot
JavascriptQingliangjiHanshuShiBiancheng/font/fontello.svg
JavascriptQingliangjiHanshuShiBiancheng/font/fontello.ttf
JavascriptQingliangjiHanshuShiBiancheng/font/fontello.woff
JavascriptQingliangjiHanshuShiBiancheng/img/__init__.py
JavascriptQingliangjiHanshuShiBiancheng/img/annotator-glyph-sprite.png
JavascriptQingliangjiHanshuShiBiancheng/img/annotator-icon-sprite.png
JavascriptQingliangjiHanshuShiBiancheng/img/apple-touch-icon.png
JavascriptQingliangjiHanshuShiBiancheng/img/cancelfullscreen.png
JavascriptQingliangjiHanshuShiBiancheng/img/close.png
JavascriptQingliangjiHanshuShiBiancheng/img/fullscreen.png
JavascriptQingliangjiHanshuShiBiancheng/img/loader.gif
JavascriptQingliangjiHanshuShiBiancheng/img/menu-icon.png
JavascriptQingliangjiHanshuShiBiancheng/img/save.png
JavascriptQingliangjiHanshuShiBiancheng/img/saved.png
JavascriptQingliangjiHanshuShiBiancheng/img/settings-s.png
JavascriptQingliangjiHanshuShiBiancheng/img/settings.png
JavascriptQingliangjiHanshuShiBiancheng/img/star.png
JavascriptQingliangjiHanshuShiBiancheng/js/__init__.py
JavascriptQingliangjiHanshuShiBiancheng/js/epub.js
JavascriptQingliangjiHanshuShiBiancheng/js/epub.min.js
JavascriptQingliangjiHanshuShiBiancheng/js/epub.min.map
JavascriptQingliangjiHanshuShiBiancheng/js/hooks.min.js
JavascriptQingliangjiHanshuShiBiancheng/js/hooks.min.map
javascript_qingliangji_hanshu_shi_biancheng-2024.3.2.0.dist-info/METADATA
javascript_qingliangji_hanshu_shi_biancheng-2024.3.2.0.dist-info/WHEEL
javascript_qingliangji_hanshu_shi_biancheng-2024.3.2.0.dist-info/entry_points.txt
javascript_qingliangji_hanshu_shi_biancheng-2024.3.2.0.dist-info/top_level.txt
javascript_qingliangji_hanshu_shi_biancheng-2024.3.2.0.dist-info/RECORD
